LICENSE.txt
MANIFEST.in
README.rst
requirements-dev.txt
setup.cfg
setup.py
str2type/__init__.py
str2type/core.py
str2type/deprecated.py
str2type/ext.py
str2type/pycompat.py
str2type.egg-info/PKG-INFO
str2type.egg-info/SOURCES.txt
str2type.egg-info/dependency_links.txt
str2type.egg-info/top_level.txt
str2type.egg-info/zip-safe
tests/__init__.py
tests/data.py
tests/test_core.py
tests/test_deprecated.py
tests/test_ext.py