Metadata-Version: 1.1
Name: str2type
Version: 0.4.1
Summary: Convert a string representation of an int, float, None, True, False, or JSON to its native type.  For None, True, and False, case is irrelevant.
Home-page: https://github.com/geowurster/str2type
Author: Kevin Wurster
Author-email: wursterk@gmail.com
License: New BSD License
